ai3_workers/__init__.py
ai3_workers/core/__init__.py
ai3_workers/core/components.py
ai3_workers/core/config.py
ai3_workers/core/i18n.py
ai3_workers-0.1.3.dist-info/METADATA
ai3_workers-0.1.3.dist-info/WHEEL
ai3_workers-0.1.3.dist-info/RECORD
