Metadata-Version: 2.1
Name: ai3-workers
Version: 0.1.3
Summary: Utilities and standard configurations for creating Streamlit workers in the AIAIAI ecosystem
Home-page: https://hub.nucleoo.com/aiaiai/ai3-workers
License: CC-BY-NC-4.0
Keywords: streamlit,aiaiai,workers,utilities
Author: Martijn Schouten
Author-email: martijn@aiaiai.eu
Requires-Python: >=3.11,<4.0
Classifier: Development Status :: 4 - Beta
Classifier: Intended Audience :: Developers
Classifier: License :: Other/Proprietary License
Classifier: Operating System :: OS Independent
Classifier: Programming Language :: Python :: 3
Classifier: Programming Language :: Python :: 3.11
Classifier: Programming Language :: Python :: 3.10
Classifier: Programming Language :: Python :: 3.9
Requires-Dist: streamlit (>=1.40.2,<2.0.0)
Requires-Dist: typing-extensions (>=4.12.2,<5.0.0)
Project-URL: Repository, https://hub.nucleoo.com/aiaiai/ai3-workers
